ddtestpy/__init__.py
ddtestpy/internal/__init__.py
ddtestpy/internal/api_client.py
ddtestpy/internal/constants.py
ddtestpy/internal/coverage_api.py
ddtestpy/internal/git.py
ddtestpy/internal/http.py
ddtestpy/internal/logging.py
ddtestpy/internal/platform.py
ddtestpy/internal/retries.py
ddtestpy/internal/retry_handlers.py
ddtestpy/internal/session_manager.py
ddtestpy/internal/test_data.py
ddtestpy/internal/utils.py
ddtestpy/internal/writer.py
ddtestpy/internal/ddtrace/__init__.py
ddtestpy/internal/ddtrace/span_processor.py
ddtestpy/internal/pytest/__init__.py
ddtestpy/internal/pytest/plugin.py
ddtestpy/vendor/ddtrace_coverage/__init__.py
ddtestpy/vendor/ddtrace_coverage/assembly.py
ddtestpy/vendor/ddtrace_coverage/cache.py
ddtestpy/vendor/ddtrace_coverage/code.py
ddtestpy/vendor/ddtrace_coverage/context.py
ddtestpy/vendor/ddtrace_coverage/coverage_lines.py
ddtestpy/vendor/ddtrace_coverage/inspection.py
ddtestpy/vendor/ddtrace_coverage/installer.py
ddtestpy/vendor/ddtrace_coverage/instrumentation.py
ddtestpy/vendor/ddtrace_coverage/instrumentation_py3_10.py
ddtestpy/vendor/ddtrace_coverage/instrumentation_py3_11.py
ddtestpy/vendor/ddtrace_coverage/instrumentation_py3_12.py
ddtestpy/vendor/ddtrace_coverage/instrumentation_py3_13.py
ddtestpy/vendor/ddtrace_coverage/instrumentation_py3_8.py
ddtestpy/vendor/ddtrace_coverage/module.py
ddtestpy/vendor/ddtrace_coverage/multiprocessing_coverage.py
ddtestpy/vendor/ddtrace_coverage/packages.py
ddtestpy/vendor/ddtrace_coverage/report.py
ddtestpy/vendor/ddtrace_coverage/third-party.tar.gz
ddtestpy/vendor/ddtrace_coverage/threading_coverage.py
ddtestpy/vendor/ddtrace_coverage/util.py
ddtestpy/vendor/ddtrace_coverage/utils.py
ddtestpy/vendor/ddtrace_coverage/bytecode_injection/__init__.py
ddtestpy/vendor/ddtrace_coverage/bytecode_injection/core.py
ddtestpy-0.1.0.dist-info/METADATA
ddtestpy-0.1.0.dist-info/WHEEL
ddtestpy-0.1.0.dist-info/entry_points.txt
ddtestpy-0.1.0.dist-info/licenses/LICENSE
ddtestpy-0.1.0.dist-info/licenses/LICENSE-3rdparty.csv
ddtestpy-0.1.0.dist-info/licenses/NOTICE
ddtestpy-0.1.0.dist-info/RECORD
