Metadata-Version: 2.4
Name: ddtestpy
Version: 0.1.0
License-Expression: Apache-2.0
License-File: LICENSE
License-File: LICENSE-3rdparty.csv
License-File: NOTICE
Requires-Dist: bytecode>=0.15.0
Requires-Dist: msgpack>=1.0.0
